melony/__init__.py
melony/logger.py
melony/core/__init__.py
melony/core/brokers.py
melony/core/consts.py
melony/core/consumers.py
melony/core/dto.py
melony/core/publishers.py
melony/core/result_backends.py
melony/core/task_converters.py
melony/core/task_executor.py
melony/core/task_finders.py
melony/core/task_wrappers.py
melony/core/tasks.py
melony/redis_broker/__init__.py
melony/redis_broker/brokers.py
melony/redis_broker/consumers.py
melony/redis_broker/publishers.py
melony/redis_broker/result_backends.py
melony-1.0.4.dist-info/METADATA
melony-1.0.4.dist-info/WHEEL
melony-1.0.4.dist-info/top_level.txt
melony-1.0.4.dist-info/RECORD
