Metadata-Version: 2.1
Name: melony
Version: 1.0.4
Summary: Multisync task manager for python
Home-page: https://melony-python.com/
Author: wimble3
Author-email: wimble@internet.ru
License: UNKNOWN
Project-URL: Documentation, https://melony-python.com/docs
Keywords: task manager python melony
Platform: UNKNOWN
Classifier: Programming Language :: Python :: 3.12
Classifier: License :: OSI Approved :: MIT License
Classifier: Operating System :: OS Independent
Requires-Python: >=3.12
Requires-Dist: asyncio (>=4.0.0)
Requires-Dist: classes (>=0.4.1)
Requires-Dist: pytest-asyncio (>=1.1.0)
Requires-Dist: pytest (>=8.4.1)
Requires-Dist: redis (>=6.4.0)
Requires-Dist: setuptools (>=80.10.2)
Requires-Dist: wemake-python-styleguide (>=1.3.0)
